wink_sdk_engine_client/__init__.py
wink_sdk_engine_client/api_client.py
wink_sdk_engine_client/api_response.py
wink_sdk_engine_client/configuration.py
wink_sdk_engine_client/exceptions.py
wink_sdk_engine_client/py.typed
wink_sdk_engine_client/rest.py
wink_sdk_engine_client/api/__init__.py
wink_sdk_engine_client/api/configuration_api.py
wink_sdk_engine_client/models/__init__.py
wink_sdk_engine_client/models/child_non_authenticated_entity.py
wink_sdk_engine_client/models/customization_client_non_authenticated_entity.py
wink_sdk_engine_client/models/customization_theme_colors_non_authenticated_entity.py
wink_sdk_engine_client/models/engine_client_non_authenticated_entity.py
wink_sdk_engine_client/models/engine_configuration_theme_colors_non_authenticated_entity.py
wink_sdk_engine_client/models/engine_configuration_theme_non_authenticated_entity.py
wink_sdk_engine_client/models/generic_error_message.py
wink_sdk_engine_client/models/room_configuration_non_authenticated_entity.py
wink_sdk_engine_client/models/show_customization_by_id400_response.py
wink_sdk_engine_client/models/show_engine_configuration400_response.py
wink_sdk_engine_client-0.0.57.dist-info/licenses/LICENSE
wink_sdk_engine_client-0.0.57.dist-info/METADATA
wink_sdk_engine_client-0.0.57.dist-info/WHEEL
wink_sdk_engine_client-0.0.57.dist-info/top_level.txt
wink_sdk_engine_client-0.0.57.dist-info/RECORD
